{"numberOfSchools": 16, "numberOfPages": 2, "schoolList": [{"schoolid": "061970002363", "schoolName": "Alta Elementary", "phone": "(559) 305-7210", "url": "https://www.schooldigger.com/go/CA/schools/1970002363/school.aspx", "urlCompare": "https://www.schooldigger.com/go/CA/schools/1970002363/search.aspx", "address": {"street": "21771 E. Parlier Ave.", "city": "Reedley", "state": "CA", "stateFull": "California", "zip": "93654", "zip4": "9535", "cityURL": "https://www.schooldigger.com/go/CA/city/Reedley/search.aspx", "zipURL": "https://www.schooldigger.com/go/CA/zip/93654/search.aspx", "html": "21771 E. Parlier Ave.<br />Reedley, CA 93654-9535"}, "lowGrade": "K", "highGrade": "5", "schoolLevel": "Elementary", "isCharterSchool": "No", "isMagnetSchool": "No", "isVirtualSchool": "No", "isTitleISchool": "Yes", "isTitleISchoolwideSchool": "No", "district": {"districtID": "0619700", "districtName": "Kings Canyon Joint Unified", "url": "https://www.schooldigger.com/go/CA/district/19700/search.aspx", "rankURL": "https://www.schooldigger.com/go/CA/districtrank.aspx?finddistrict=19700"}, "county": {"countyName": "Fresno County", "countyURL": "https://www.schooldigger.com/go/CA/county/Fresno+County/search.aspx"}, "rankHistory": [{"year": 2019, "rank": 2778, "rankOf": 5789, "rankStars": 3, "rankLevel": "Elementary", "rankStatewidePercentage": 52.01, "averageStandardScore": 46.74435}, {"year": 2018, "rank": 3594, "rankOf": 5662, "rankStars": 2, "rankLevel": "Elementary", "rankStatewidePercentage": 36.52, "averageStandardScore": 33.06661}], "rankMovement": 816, "schoolYearlyDetails": [{"year": 2020, "numberOfStudents": 362, "percentFreeDiscLunch": 85.91, "percentofAfricanAmericanStudents": 0.0, "percentofAsianStudents": 0.55, "percentofHispanicStudents": 91.71, "percentofIndianStudents": 0.0, "percentofPacificIslanderStudents": 0.0, "percentofWhiteStudents": 6.91, "percentofTwoOrMoreRaceStudents": 0.83, "percentofUnspecifiedRaceStudents": null, "teachersFulltime": null, "pupilTeacherRatio": null, "numberofAfricanAmericanStudents": 0, "numberofAsianStudents": 2, "numberofHispanicStudents": 332, "numberofIndianStudents": 0, "numberofPacificIslanderStudents": 0, "numberofWhiteStudents": 25, "numberofTwoOrMoreRaceStudents": 3, "numberofUnspecifiedRaceStudents": null}], "isPrivate": false, "privateDays": null, "privateHours": null, "privateHasLibrary": null, "privateCoed": null, "privateOrientation": null, "hasBoundary": true}, {"schoolid": "061970002366", "schoolName": "General Grant Middle", "phone": "(559) 305-7330", "url": "https://www.schooldigger.com/go/CA/schools/1970002366/school.aspx", "urlCompare": "https://www.schooldigger.com/go/CA/schools/1970002366/search.aspx", "address": {"street": "360 N. E. Ave.", "city": "Reedley", "state": "CA", "stateFull": "California", "zip": "93654", "zip4": "2510", "cityURL": "https://www.schooldigger.com/go/CA/city/Reedley/search.aspx", "zipURL": "https://www.schooldigger.com/go/CA/zip/93654/search.aspx", "html": "360 N. E. Ave.<br />Reedley, CA 93654-2510"}, "lowGrade": "6", "highGrade": "8", "schoolLevel": "Middle", "isCharterSchool": "No", "isMagnetSchool": "No", "isVirtualSchool": "No", "isTitleISchool": "Yes", "isTitleISchoolwideSchool": "No", "district": {"districtID": "0619700", "districtName": "Kings Canyon Joint Unified", "url": "https://www.schooldigger.com/go/CA/district/19700/search.aspx", "rankURL": "https://www.schooldigger.com/go/CA/districtrank.aspx?finddistrict=19700"}, "county": {"countyName": "Fresno County", "countyURL": "https://www.schooldigger.com/go/CA/county/Fresno+County/search.aspx"}, "rankHistory": [{"year": 2019, "rank": 662, "rankOf": 2715, "rankStars": 4, "rankLevel": "Middle", "rankStatewidePercentage": 75.62, "averageStandardScore": 71.37743}, {"year": 2018, "rank": 740, "rankOf": 2480, "rankStars": 4, "rankLevel": "Middle", "rankStatewidePercentage": 70.16, "averageStandardScore": 65.37745}], "rankMovement": 78, "schoolYearlyDetails": [{"year": 2020, "numberOfStudents": 536, "percentFreeDiscLunch": 92.54, "percentofAfricanAmericanStudents": 0.0, "percentofAsianStudents": 0.75, "percentofHispanicStudents": 96.08, "percentofIndianStudents": 0.0, "percentofPacificIslanderStudents": 0.0, "percentofWhiteStudents": 2.43, "percentofTwoOrMoreRaceStudents": 0.75, "percentofUnspecifiedRaceStudents": null, "teachersFulltime": null, "pupilTeacherRatio": null, "numberofAfricanAmericanStudents": 0, "numberofAsianStudents": 4, "numberofHispanicStudents": 515, "numberofIndianStudents": 0, "numberofPacificIslanderStudents": 0, "numberofWhiteStudents": 13, "numberofTwoOrMoreRaceStudents": 4, "numberofUnspecifiedRaceStudents": null}], "isPrivate": false, "privateDays": null, "privateHours": null, "privateHasLibrary": null, "privateCoed": null, "privateOrientation": null, "hasBoundary": true}, {"schoolid": "061970002367", "schoolName": "Great Western Elementary", "phone": "(559) 305-7220", "url": "https://www.schooldigger.com/go/CA/schools/1970002367/school.aspx", "urlCompare": "https://www.schooldigger.com/go/CA/schools/1970002367/search.aspx", "address": {"street": "5051 S. Frankwood Ave.", "city": "Reedley", "state": "CA", "stateFull": "California", "zip": "93654", "zip4": "9779", "cityURL": "https://www.schooldigger.com/go/CA/city/Reedley/search.aspx", "zipURL": "https://www.schooldigger.com/go/CA/zip/93654/search.aspx", "html": "5051 S. Frankwood Ave.<br />Reedley, CA 93654-9779"}, "lowGrade": "K", "highGrade": "5", "schoolLevel": "Elementary", "isCharterSchool": "No", "isMagnetSchool": "No", "isVirtualSchool": "No", "isTitleISchool": "Yes", "isTitleISchoolwideSchool": "No", "district": {"districtID": "0619700", "districtName": "Kings Canyon Joint Unified", "url": "https://www.schooldigger.com/go/CA/district/19700/search.aspx", "rankURL": "https://www.schooldigger.com/go/CA/districtrank.aspx?finddistrict=19700"}, "county": {"countyName": "Fresno County", "countyURL": "https://www.schooldigger.com/go/CA/county/Fresno+County/search.aspx"}, "rankHistory": [{"year": 2019, "rank": 2166, "rankOf": 5789, "rankStars": 3, "rankLevel": "Elementary", "rankStatewidePercentage": 62.58, "averageStandardScore": 58.20269}, {"year": 2018, "rank": 3124, "rankOf": 5662, "rankStars": 2, "rankLevel": "Elementary", "rankStatewidePercentage": 44.83, "averageStandardScore": 40.49144}], "rankMovement": 958, "schoolYearlyDetails": [{"year": 2020, "numberOfStudents": 325, "percentFreeDiscLunch": 85.23, "percentofAfricanAmericanStudents": 0.62, "percentofAsianStudents": 0.92, "percentofHispanicStudents": 87.08, "percentofIndianStudents": 0.31, "percentofPacificIslanderStudents": 0.0, "percentofWhiteStudents": 10.46, "percentofTwoOrMoreRaceStudents": 0.62, "percentofUnspecifiedRaceStudents": null, "teachersFulltime": null, "pupilTeacherRatio": null, "numberofAfricanAmericanStudents": 2, "numberofAsianStudents": 3, "numberofHispanicStudents": 283, "numberofIndianStudents": 1, "numberofPacificIslanderStudents": 0, "numberofWhiteStudents": 34, "numberofTwoOrMoreRaceStudents": 2, "numberofUnspecifiedRaceStudents": null}], "isPrivate": false, "privateDays": null, "privateHours": null, "privateHasLibrary": null, "privateCoed": null, "privateOrientation": null, "hasBoundary": true}, {"schoolid": "061970002368", "schoolName": "Jefferson Elementary", "phone": "(559) 305-7230", "url": "https://www.schooldigger.com/go/CA/schools/1970002368/school.aspx", "urlCompare": "https://www.schooldigger.com/go/CA/schools/1970002368/search.aspx", "address": {"street": "1037 E. Duff Ave.", "city": "Reedley", "state": "CA", "stateFull": "California", "zip": "93654", "zip4": "3505", "cityURL": "https://www.schooldigger.com/go/CA/city/Reedley/search.aspx", "zipURL": "https://www.schooldigger.com/go/CA/zip/93654/search.aspx", "html": "1037 E. Duff Ave.<br />Reedley, CA 93654-3505"}, "lowGrade": "K", "highGrade": "5", "schoolLevel": "Elementary", "isCharterSchool": "No", "isMagnetSchool": "No", "isVirtualSchool": "No", "isTitleISchool": "Yes", "isTitleISchoolwideSchool": "No", "district": {"districtID": "0619700", "districtName": "Kings Canyon Joint Unified", "url": "https://www.schooldigger.com/go/CA/district/19700/search.aspx", "rankURL": "https://www.schooldigger.com/go/CA/districtrank.aspx?finddistrict=19700"}, "county": {"countyName": "Fresno County", "countyURL": "https://www.schooldigger.com/go/CA/county/Fresno+County/search.aspx"}, "rankHistory": [{"year": 2019, "rank": 2347, "rankOf": 5789, "rankStars": 3, "rankLevel": "Elementary", "rankStatewidePercentage": 59.46, "averageStandardScore": 54.58117}, {"year": 2018, "rank": 2627, "rankOf": 5662, "rankStars": 3, "rankLevel": "Elementary", "rankStatewidePercentage": 53.6, "averageStandardScore": 48.7477}], "rankMovement": 280, "schoolYearlyDetails": [{"year": 2020, "numberOfStudents": 393, "percentFreeDiscLunch": 93.13, "percentofAfricanAmericanStudents": 0.25, "percentofAsianStudents": 0.25, "percentofHispanicStudents": 97.46, "percentofIndianStudents": 0.25, "percentofPacificIslanderStudents": 0.0, "percentofWhiteStudents": 1.27, "percentofTwoOrMoreRaceStudents": 0.51, "percentofUnspecifiedRaceStudents": null, "teachersFulltime": null, "pupilTeacherRatio": null, "numberofAfricanAmericanStudents": 1, "numberofAsianStudents": 1, "numberofHispanicStudents": 383, "numberofIndianStudents": 1, "numberofPacificIslanderStudents": 0, "numberofWhiteStudents": 5, "numberofTwoOrMoreRaceStudents": 2, "numberofUnspecifiedRaceStudents": null}], "isPrivate": false, "privateDays": null, "privateHours": null, "privateHasLibrary": null, "privateCoed": null, "privateOrientation": null, "hasBoundary": true}, {"schoolid": "061970013511", "schoolName": "KC KIDS Pre-School", "phone": "(559) 305-7130", "url": "https://www.schooldigger.com/go/CA/schools/1970013511/school.aspx", "urlCompare": "https://www.schooldigger.com/go/CA/schools/1970013511/search.aspx", "address": {"street": "1220 E. Washington Ave.", "city": "Reedley", "state": "CA", "stateFull": "California", "zip": "93654", "zip4": "3595", "cityURL": "https://www.schooldigger.com/go/CA/city/Reedley/search.aspx", "zipURL": "https://www.schooldigger.com/go/CA/zip/93654/search.aspx", "html": "1220 E. Washington Ave.<br />Reedley, CA 93654-3595"}, "lowGrade": "", "highGrade": "", "schoolLevel": "", "isCharterSchool": "No", "isMagnetSchool": "(n/a)", "isVirtualSchool": "(n/a)", "isTitleISchool": "(n/a)", "isTitleISchoolwideSchool": "(n/a)", "district": {"districtID": "0619700", "districtName": "Kings Canyon Joint Unified", "url": "https://www.schooldigger.com/go/CA/district/19700/search.aspx", "rankURL": "https://www.schooldigger.com/go/CA/districtrank.aspx?finddistrict=19700"}, "county": {"countyName": "Fresno County", "countyURL": "https://www.schooldigger.com/go/CA/county/Fresno+County/search.aspx"}, "rankHistory": null, "rankMovement": null, "schoolYearlyDetails": [], "isPrivate": false, "privateDays": null, "privateHours": null, "privateHasLibrary": null, "privateCoed": null, "privateOrientation": null, "hasBoundary": true}, {"schoolid": "061970013620", "schoolName": "Kings Canyon Unified School District Wide Preschools", "phone": "(559) 305-7279", "url": "https://www.schooldigger.com/go/CA/schools/1970013620/school.aspx", "urlCompare": "https://www.schooldigger.com/go/CA/schools/1970013620/search.aspx", "address": {"street": "1801 Tenth St.", "city": "Reedley", "state": "CA", "stateFull": "California", "zip": "93654", "zip4": "2427", "cityURL": "https://www.schooldigger.com/go/CA/city/Reedley/search.aspx", "zipURL": "https://www.schooldigger.com/go/CA/zip/93654/search.aspx", "html": "1801 Tenth St.<br />Reedley, CA 93654-2427"}, "lowGrade": "", "highGrade": "", "schoolLevel": "", "isCharterSchool": "No", "isMagnetSchool": "(n/a)", "isVirtualSchool": "(n/a)", "isTitleISchool": "(n/a)", "isTitleISchoolwideSchool": "(n/a)", "district": {"districtID": "0619700", "districtName": "Kings Canyon Joint Unified", "url": "https://www.schooldigger.com/go/CA/district/19700/search.aspx", "rankURL": "https://www.schooldigger.com/go/CA/districtrank.aspx?finddistrict=19700"}, "county": {"countyName": "Fresno County", "countyURL": "https://www.schooldigger.com/go/CA/county/Fresno+County/search.aspx"}, "rankHistory": null, "rankMovement": null, "schoolYearlyDetails": [], "isPrivate": false, "privateDays": null, "privateHours": null, "privateHasLibrary": null, "privateCoed": null, "privateOrientation": null, "hasBoundary": true}, {"schoolid": "069999953814", "schoolName": "Klip International", "phone": "(559) 246-7574", "url": "https://www.schooldigger.com/go/CA/schools/9999953814/school.aspx", "urlCompare": "https://www.schooldigger.com/go/CA/schools/9999953814/search.aspx", "address": {"street": "5018 Ave 416", "city": "Reedley", "state": "CA", "stateFull": "California", "zip": "93654", "zip4": "", "cityURL": "https://www.schooldigger.com/go/CA/city/Reedley/search.aspx", "zipURL": "https://www.schooldigger.com/go/CA/zip/93654/search.aspx", "html": "5018 Ave 416<br />Reedley, CA 93654"}, "lowGrade": "K", "highGrade": "12", "schoolLevel": "Private", "isCharterSchool": "(n/a)", "isMagnetSchool": "(n/a)", "isVirtualSchool": "(n/a)", "isTitleISchool": "(n/a)", "isTitleISchoolwideSchool": "(n/a)", "county": {"countyName": "Tulare County", "countyURL": "https://www.schooldigger.com/go/CA/county/Tulare+County/search.aspx"}, "rankHistory": null, "rankMovement": null, "schoolYearlyDetails": [{"year": 2018, "numberOfStudents": 44, "percentFreeDiscLunch": null, "percentofAfricanAmericanStudents": 0.0, "percentofAsianStudents": 0.0, "percentofHispanicStudents": 79.55, "percentofIndianStudents": 0.0, "percentofPacificIslanderStudents": 0.0, "percentofWhiteStudents": 20.45, "percentofTwoOrMoreRaceStudents": 0.0, "percentofUnspecifiedRaceStudents": null, "teachersFulltime": 6.8, "pupilTeacherRatio": 6.4, "numberofAfricanAmericanStudents": 0, "numberofAsianStudents": 0, "numberofHispanicStudents": 35, "numberofIndianStudents": 0, "numberofPacificIslanderStudents": 0, "numberofWhiteStudents": 9, "numberofTwoOrMoreRaceStudents": 0, "numberofUnspecifiedRaceStudents": null}], "isPrivate": true, "privateDays": 175, "privateHours": 6.0, "privateHasLibrary": true, "privateCoed": "Coed", "privateOrientation": "Pentecostal", "hasBoundary": null}, {"schoolid": "061970002370", "schoolName": "Lincoln Elementary", "phone": "(559) 305-7240", "url": "https://www.schooldigger.com/go/CA/schools/1970002370/school.aspx", "urlCompare": "https://www.schooldigger.com/go/CA/schools/1970002370/search.aspx", "address": {"street": "374 E. N. Ave.", "city": "Reedley", "state": "CA", "stateFull": "California", "zip": "93654", "zip4": "2535", "cityURL": "https://www.schooldigger.com/go/CA/city/Reedley/search.aspx", "zipURL": "https://www.schooldigger.com/go/CA/zip/93654/search.aspx", "html": "374 E. N. Ave.<br />Reedley, CA 93654-2535"}, "lowGrade": "K", "highGrade": "5", "schoolLevel": "Elementary", "isCharterSchool": "No", "isMagnetSchool": "No", "isVirtualSchool": "No", "isTitleISchool": "Yes", "isTitleISchoolwideSchool": "No", "district": {"districtID": "0619700", "districtName": "Kings Canyon Joint Unified", "url": "https://www.schooldigger.com/go/CA/district/19700/search.aspx", "rankURL": "https://www.schooldigger.com/go/CA/districtrank.aspx?finddistrict=19700"}, "county": {"countyName": "Fresno County", "countyURL": "https://www.schooldigger.com/go/CA/county/Fresno+County/search.aspx"}, "rankHistory": [{"year": 2019, "rank": 4631, "rankOf": 5789, "rankStars": 1, "rankLevel": "Elementary", "rankStatewidePercentage": 20.0, "averageStandardScore": 21.98157}, {"year": 2018, "rank": 3572, "rankOf": 5662, "rankStars": 2, "rankLevel": "Elementary", "rankStatewidePercentage": 36.91, "averageStandardScore": 33.42892}], "rankMovement": -1059, "schoolYearlyDetails": [{"year": 2020, "numberOfStudents": 303, "percentFreeDiscLunch": 96.04, "percentofAfricanAmericanStudents": 0.0, "percentofAsianStudents": 0.0, "percentofHispanicStudents": 99.01, "percentofIndianStudents": 0.33, "percentofPacificIslanderStudents": 0.0, "percentofWhiteStudents": 0.66, "percentofTwoOrMoreRaceStudents": 0.0, "percentofUnspecifiedRaceStudents": null, "teachersFulltime": null, "pupilTeacherRatio": null, "numberofAfricanAmericanStudents": 0, "numberofAsianStudents": 0, "numberofHispanicStudents": 300, "numberofIndianStudents": 1, "numberofPacificIslanderStudents": 0, "numberofWhiteStudents": 2, "numberofTwoOrMoreRaceStudents": 0, "numberofUnspecifiedRaceStudents": null}], "isPrivate": false, "privateDays": null, "privateHours": null, "privateHasLibrary": null, "privateCoed": null, "privateOrientation": null, "hasBoundary": true}, {"schoolid": "061970009385", "schoolName": "Mountain View (Alternative)", "phone": "(559) 305-7080", "url": "https://www.schooldigger.com/go/CA/schools/1970009385/school.aspx", "urlCompare": "https://www.schooldigger.com/go/CA/schools/1970009385/search.aspx", "address": {"street": "877 E. N. Ave.", "city": "Reedley", "state": "CA", "stateFull": "California", "zip": "93654", "zip4": "2426", "cityURL": "https://www.schooldigger.com/go/CA/city/Reedley/search.aspx", "zipURL": "https://www.schooldigger.com/go/CA/zip/93654/search.aspx", "html": "877 E. N. Ave.<br />Reedley, CA 93654-2426"}, "lowGrade": "K", "highGrade": "12", "schoolLevel": "Other", "isCharterSchool": "No", "isMagnetSchool": "No", "isVirtualSchool": "No", "isTitleISchool": "Yes", "isTitleISchoolwideSchool": "No", "district": {"districtID": "0619700", "districtName": "Kings Canyon Joint Unified", "url": "https://www.schooldigger.com/go/CA/district/19700/search.aspx", "rankURL": "https://www.schooldigger.com/go/CA/districtrank.aspx?finddistrict=19700"}, "county": {"countyName": "Fresno County", "countyURL": "https://www.schooldigger.com/go/CA/county/Fresno+County/search.aspx"}, "rankHistory": null, "rankMovement": null, "schoolYearlyDetails": [{"year": 2020, "numberOfStudents": 190, "percentFreeDiscLunch": 79.47, "percentofAfricanAmericanStudents": 0.0, "percentofAsianStudents": 0.53, "percentofHispanicStudents": 85.79, "percentofIndianStudents": 0.53, "percentofPacificIslanderStudents": 0.0, "percentofWhiteStudents": 11.05, "percentofTwoOrMoreRaceStudents": 2.11, "percentofUnspecifiedRaceStudents": null, "teachersFulltime": null, "pupilTeacherRatio": null, "numberofAfricanAmericanStudents": 0, "numberofAsianStudents": 1, "numberofHispanicStudents": 163, "numberofIndianStudents": 1, "numberofPacificIslanderStudents": 0, "numberofWhiteStudents": 21, "numberofTwoOrMoreRaceStudents": 4, "numberofUnspecifiedRaceStudents": null}], "isPrivate": false, "privateDays": null, "privateHours": null, "privateHasLibrary": null, "privateCoed": null, "privateOrientation": null, "hasBoundary": false}, {"schoolid": "061970002373", "schoolName": "Navelencia Middle", "phone": "(559) 305-7350", "url": "https://www.schooldigger.com/go/CA/schools/1970002373/school.aspx", "urlCompare": "https://www.schooldigger.com/go/CA/schools/1970002373/search.aspx", "address": {"street": "22620 E. Wahtoke Ave.", "city": "Reedley", "state": "CA", "stateFull": "California", "zip": "93654", "zip4": "9604", "cityURL": "https://www.schooldigger.com/go/CA/city/Reedley/search.aspx", "zipURL": "https://www.schooldigger.com/go/CA/zip/93654/search.aspx", "html": "22620 E. Wahtoke Ave.<br />Reedley, CA 93654-9604"}, "lowGrade": "6", "highGrade": "8", "schoolLevel": "Middle", "isCharterSchool": "No", "isMagnetSchool": "No", "isVirtualSchool": "No", "isTitleISchool": "Yes", "isTitleISchoolwideSchool": "No", "district": {"districtID": "0619700", "districtName": "Kings Canyon Joint Unified", "url": "https://www.schooldigger.com/go/CA/district/19700/search.aspx", "rankURL": "https://www.schooldigger.com/go/CA/districtrank.aspx?finddistrict=19700"}, "county": {"countyName": "Fresno County", "countyURL": "https://www.schooldigger.com/go/CA/county/Fresno+County/search.aspx"}, "rankHistory": [{"year": 2019, "rank": 1395, "rankOf": 2715, "rankStars": 2, "rankLevel": "Middle", "rankStatewidePercentage": 48.62, "averageStandardScore": 41.621}, {"year": 2018, "rank": 1122, "rankOf": 2480, "rankStars": 3, "rankLevel": "Middle", "rankStatewidePercentage": 54.76, "averageStandardScore": 48.795}], "rankMovement": -273, "schoolYearlyDetails": [{"year": 2020, "numberOfStudents": 361, "percentFreeDiscLunch": 90.3, "percentofAfricanAmericanStudents": 0.0, "percentofAsianStudents": 1.11, "percentofHispanicStudents": 88.64, "percentofIndianStudents": 0.0, "percentofPacificIslanderStudents": 0.0, "percentofWhiteStudents": 8.59, "percentofTwoOrMoreRaceStudents": 1.66, "percentofUnspecifiedRaceStudents": null, "teachersFulltime": null, "pupilTeacherRatio": null, "numberofAfricanAmericanStudents": 0, "numberofAsianStudents": 4, "numberofHispanicStudents": 320, "numberofIndianStudents": 0, "numberofPacificIslanderStudents": 0, "numberofWhiteStudents": 31, "numberofTwoOrMoreRaceStudents": 6, "numberofUnspecifiedRaceStudents": null}], "isPrivate": false, "privateDays": null, "privateHours": null, "privateHasLibrary": null, "privateCoed": null, "privateOrientation": null, "hasBoundary": true}]}