{"numberOfSchools": 11, "numberOfPages": 2, "schoolList": [{"schoolid": "063360005184", "schoolName": "Crestmont Elementary", "phone": "(916) 771-1750", "url": "https://www.schooldigger.com/go/CA/schools/3360005184/school.aspx", "urlCompare": "https://www.schooldigger.com/go/CA/schools/3360005184/search.aspx", "address": {"street": "1501 Sheridan Ave.", "city": "Roseville", "state": "CA", "stateFull": "California", "zip": "95661", "zip4": "5724", "cityURL": "https://www.schooldigger.com/go/CA/city/Roseville/search.aspx", "zipURL": "https://www.schooldigger.com/go/CA/zip/95661/search.aspx", "html": "1501 Sheridan Ave.<br />Roseville, CA 95661-5724"}, "lowGrade": "K", "highGrade": "5", "schoolLevel": "Elementary", "isCharterSchool": "No", "isMagnetSchool": "No", "isVirtualSchool": "No", "isTitleISchool": "No", "isTitleISchoolwideSchool": "No", "district": {"districtID": "0633600", "districtName": "Roseville City Elementary", "url": "https://www.schooldigger.com/go/CA/district/33600/search.aspx", "rankURL": "https://www.schooldigger.com/go/CA/districtrank.aspx?finddistrict=33600"}, "county": {"countyName": "Placer County", "countyURL": "https://www.schooldigger.com/go/CA/county/Placer+County/search.aspx"}, "rankHistory": [{"year": 2019, "rank": 1664, "rankOf": 5789, "rankStars": 4, "rankLevel": "Elementary", "rankStatewidePercentage": 71.26, "averageStandardScore": 68.62088}, {"year": 2018, "rank": 1701, "rankOf": 5662, "rankStars": 3, "rankLevel": "Elementary", "rankStatewidePercentage": 69.96, "averageStandardScore": 67.59805}], "rankMovement": 37, "schoolYearlyDetails": [{"year": 2020, "numberOfStudents": 478, "percentFreeDiscLunch": 37.87, "percentofAfricanAmericanStudents": 1.26, "percentofAsianStudents": 3.77, "percentofHispanicStudents": 24.06, "percentofIndianStudents": 0.21, "percentofPacificIslanderStudents": 0.84, "percentofWhiteStudents": 62.97, "percentofTwoOrMoreRaceStudents": 6.9, "percentofUnspecifiedRaceStudents": null, "teachersFulltime": null, "pupilTeacherRatio": null, "numberofAfricanAmericanStudents": 6, "numberofAsianStudents": 18, "numberofHispanicStudents": 115, "numberofIndianStudents": 1, "numberofPacificIslanderStudents": 4, "numberofWhiteStudents": 301, "numberofTwoOrMoreRaceStudents": 33, "numberofUnspecifiedRaceStudents": null}], "isPrivate": false, "privateDays": null, "privateHours": null, "privateHasLibrary": null, "privateCoed": null, "privateOrientation": null, "hasBoundary": true}, {"schoolid": "061308008254", "schoolName": "Excelsior Elementary", "phone": "(916) 780-2701", "url": "https://www.schooldigger.com/go/CA/schools/1308008254/school.aspx", "urlCompare": "https://www.schooldigger.com/go/CA/schools/1308008254/search.aspx", "address": {"street": "2701 Eureka Rd.", "city": "Roseville", "state": "CA", "stateFull": "California", "zip": "95661", "zip4": "6447", "cityURL": "https://www.schooldigger.com/go/CA/city/Roseville/search.aspx", "zipURL": "https://www.schooldigger.com/go/CA/zip/95661/search.aspx", "html": "2701 Eureka Rd.<br />Roseville, CA 95661-6447"}, "lowGrade": "4", "highGrade": "6", "schoolLevel": "Middle", "isCharterSchool": "No", "isMagnetSchool": "No", "isVirtualSchool": "No", "isTitleISchool": "Yes", "isTitleISchoolwideSchool": "No", "district": {"districtID": "0613080", "districtName": "Eureka Union", "url": "https://www.schooldigger.com/go/CA/district/13080/search.aspx", "rankURL": "https://www.schooldigger.com/go/CA/districtrank.aspx?finddistrict=13080"}, "county": {"countyName": "Placer County", "countyURL": "https://www.schooldigger.com/go/CA/county/Placer+County/search.aspx"}, "rankHistory": null, "rankMovement": null, "schoolYearlyDetails": [{"year": 2020, "numberOfStudents": 501, "percentFreeDiscLunch": 17.56, "percentofAfricanAmericanStudents": 2.4, "percentofAsianStudents": 10.58, "percentofHispanicStudents": 14.57, "percentofIndianStudents": 0.6, "percentofPacificIslanderStudents": 0.0, "percentofWhiteStudents": 62.28, "percentofTwoOrMoreRaceStudents": 9.58, "percentofUnspecifiedRaceStudents": null, "teachersFulltime": null, "pupilTeacherRatio": null, "numberofAfricanAmericanStudents": 12, "numberofAsianStudents": 53, "numberofHispanicStudents": 73, "numberofIndianStudents": 3, "numberofPacificIslanderStudents": 0, "numberofWhiteStudents": 312, "numberofTwoOrMoreRaceStudents": 48, "numberofUnspecifiedRaceStudents": null}], "isPrivate": false, "privateDays": null, "privateHours": null, "privateHasLibrary": null, "privateCoed": null, "privateOrientation": null, "hasBoundary": true}, {"schoolid": "063360008955", "schoolName": "George Sargeant Elementary", "phone": "(916) 771-1800", "url": "https://www.schooldigger.com/go/CA/schools/3360008955/school.aspx", "urlCompare": "https://www.schooldigger.com/go/CA/schools/3360008955/search.aspx", "address": {"street": "1200 Ridgecrest Way", "city": "Roseville", "state": "CA", "stateFull": "California", "zip": "95661", "zip4": "7308", "cityURL": "https://www.schooldigger.com/go/CA/city/Roseville/search.aspx", "zipURL": "https://www.schooldigger.com/go/CA/zip/95661/search.aspx", "html": "1200 Ridgecrest Way<br />Roseville, CA 95661-7308"}, "lowGrade": "K", "highGrade": "5", "schoolLevel": "Elementary", "isCharterSchool": "No", "isMagnetSchool": "No", "isVirtualSchool": "No", "isTitleISchool": "No", "isTitleISchoolwideSchool": "No", "district": {"districtID": "0633600", "districtName": "Roseville City Elementary", "url": "https://www.schooldigger.com/go/CA/district/33600/search.aspx", "rankURL": "https://www.schooldigger.com/go/CA/districtrank.aspx?finddistrict=33600"}, "county": {"countyName": "Placer County", "countyURL": "https://www.schooldigger.com/go/CA/county/Placer+County/search.aspx"}, "rankHistory": [{"year": 2019, "rank": 2608, "rankOf": 5789, "rankStars": 3, "rankLevel": "Elementary", "rankStatewidePercentage": 54.95, "averageStandardScore": 49.77656}, {"year": 2018, "rank": 2028, "rankOf": 5662, "rankStars": 3, "rankLevel": "Elementary", "rankStatewidePercentage": 64.18, "averageStandardScore": 60.22806}], "rankMovement": -580, "schoolYearlyDetails": [{"year": 2020, "numberOfStudents": 454, "percentFreeDiscLunch": 44.49, "percentofAfricanAmericanStudents": 1.54, "percentofAsianStudents": 2.42, "percentofHispanicStudents": 32.38, "percentofIndianStudents": 1.1, "percentofPacificIslanderStudents": 0.22, "percentofWhiteStudents": 53.74, "percentofTwoOrMoreRaceStudents": 8.59, "percentofUnspecifiedRaceStudents": null, "teachersFulltime": null, "pupilTeacherRatio": null, "numberofAfricanAmericanStudents": 7, "numberofAsianStudents": 11, "numberofHispanicStudents": 147, "numberofIndianStudents": 5, "numberofPacificIslanderStudents": 1, "numberofWhiteStudents": 244, "numberofTwoOrMoreRaceStudents": 39, "numberofUnspecifiedRaceStudents": null}], "isPrivate": false, "privateDays": null, "privateHours": null, "privateHasLibrary": null, "privateCoed": null, "privateOrientation": null, "hasBoundary": true}, {"schoolid": "069999906659", "schoolName": "Granite Bay Montessori", "phone": "(916) 791-7849", "url": "https://www.schooldigger.com/go/CA/schools/9999906659/school.aspx", "urlCompare": "https://www.schooldigger.com/go/CA/schools/9999906659/search.aspx", "address": {"street": "9330 Sierra College Blvd", "city": "Roseville", "state": "CA", "stateFull": "California", "zip": "95661", "zip4": "", "cityURL": "https://www.schooldigger.com/go/CA/city/Roseville/search.aspx", "zipURL": "https://www.schooldigger.com/go/CA/zip/95661/search.aspx", "html": "9330 Sierra College Blvd<br />Roseville, CA 95661"}, "lowGrade": "PK", "highGrade": "7", "schoolLevel": "Private", "isCharterSchool": "(n/a)", "isMagnetSchool": "(n/a)", "isVirtualSchool": "(n/a)", "isTitleISchool": "(n/a)", "isTitleISchoolwideSchool": "(n/a)", "county": {"countyName": "Placer County", "countyURL": "https://www.schooldigger.com/go/CA/county/Placer+County/search.aspx"}, "rankHistory": null, "rankMovement": null, "schoolYearlyDetails": [{"year": 2018, "numberOfStudents": 164, "percentFreeDiscLunch": null, "percentofAfricanAmericanStudents": 1.22, "percentofAsianStudents": 0.0, "percentofHispanicStudents": 0.0, "percentofIndianStudents": 0.0, "percentofPacificIslanderStudents": 0.0, "percentofWhiteStudents": 53.66, "percentofTwoOrMoreRaceStudents": 0.0, "percentofUnspecifiedRaceStudents": null, "teachersFulltime": 6.5, "pupilTeacherRatio": 13.8, "numberofAfricanAmericanStudents": 2, "numberofAsianStudents": 0, "numberofHispanicStudents": 0, "numberofIndianStudents": 0, "numberofPacificIslanderStudents": 0, "numberofWhiteStudents": 88, "numberofTwoOrMoreRaceStudents": 0, "numberofUnspecifiedRaceStudents": null}], "isPrivate": true, "privateDays": 171, "privateHours": 6.7, "privateHasLibrary": false, "privateCoed": "Coed", "privateOrientation": "Nonsectarian", "hasBoundary": false}, {"schoolid": "061308007204", "schoolName": "Maidu Elementary", "phone": "(916) 789-7910", "url": "https://www.schooldigger.com/go/CA/schools/1308007204/school.aspx", "urlCompare": "https://www.schooldigger.com/go/CA/schools/1308007204/search.aspx", "address": {"street": "1950 Johnson Ranch Dr.", "city": "Roseville", "state": "CA", "stateFull": "California", "zip": "95661", "zip4": "3749", "cityURL": "https://www.schooldigger.com/go/CA/city/Roseville/search.aspx", "zipURL": "https://www.schooldigger.com/go/CA/zip/95661/search.aspx", "html": "1950 Johnson Ranch Dr.<br />Roseville, CA 95661-3749"}, "lowGrade": "K", "highGrade": "3", "schoolLevel": "Elementary", "isCharterSchool": "No", "isMagnetSchool": "No", "isVirtualSchool": "No", "isTitleISchool": "Yes", "isTitleISchoolwideSchool": "No", "district": {"districtID": "0613080", "districtName": "Eureka Union", "url": "https://www.schooldigger.com/go/CA/district/13080/search.aspx", "rankURL": "https://www.schooldigger.com/go/CA/districtrank.aspx?finddistrict=13080"}, "county": {"countyName": "Placer County", "countyURL": "https://www.schooldigger.com/go/CA/county/Placer+County/search.aspx"}, "rankHistory": null, "rankMovement": null, "schoolYearlyDetails": [{"year": 2020, "numberOfStudents": 411, "percentFreeDiscLunch": 20.44, "percentofAfricanAmericanStudents": 2.19, "percentofAsianStudents": 8.27, "percentofHispanicStudents": 18.98, "percentofIndianStudents": 0.49, "percentofPacificIslanderStudents": 0.73, "percentofWhiteStudents": 53.53, "percentofTwoOrMoreRaceStudents": 15.82, "percentofUnspecifiedRaceStudents": null, "teachersFulltime": null, "pupilTeacherRatio": null, "numberofAfricanAmericanStudents": 9, "numberofAsianStudents": 34, "numberofHispanicStudents": 78, "numberofIndianStudents": 2, "numberofPacificIslanderStudents": 3, "numberofWhiteStudents": 220, "numberofTwoOrMoreRaceStudents": 65, "numberofUnspecifiedRaceStudents": null}], "isPrivate": false, "privateDays": null, "privateHours": null, "privateHasLibrary": null, "privateCoed": null, "privateOrientation": null, "hasBoundary": true}, {"schoolid": "069999907311", "schoolName": "Merryhill School", "phone": "(916) 783-3010", "url": "https://www.schooldigger.com/go/CA/schools/9999907311/school.aspx", "urlCompare": "https://www.schooldigger.com/go/CA/schools/9999907311/search.aspx", "address": {"street": "1115 Orlando Ave", "city": "Roseville", "state": "CA", "stateFull": "California", "zip": "95661", "zip4": "", "cityURL": "https://www.schooldigger.com/go/CA/city/Roseville/search.aspx", "zipURL": "https://www.schooldigger.com/go/CA/zip/95661/search.aspx", "html": "1115 Orlando Ave<br />Roseville, CA 95661"}, "lowGrade": "PK", "highGrade": "5", "schoolLevel": "Private", "isCharterSchool": "(n/a)", "isMagnetSchool": "(n/a)", "isVirtualSchool": "(n/a)", "isTitleISchool": "(n/a)", "isTitleISchoolwideSchool": "(n/a)", "county": {"countyName": "Placer County", "countyURL": "https://www.schooldigger.com/go/CA/county/Placer+County/search.aspx"}, "rankHistory": null, "rankMovement": null, "schoolYearlyDetails": [{"year": 2018, "numberOfStudents": 102, "percentFreeDiscLunch": null, "percentofAfricanAmericanStudents": 1.96, "percentofAsianStudents": 4.9, "percentofHispanicStudents": 6.86, "percentofIndianStudents": 0.0, "percentofPacificIslanderStudents": 0.0, "percentofWhiteStudents": 69.61, "percentofTwoOrMoreRaceStudents": 0.0, "percentofUnspecifiedRaceStudents": null, "teachersFulltime": 13.0, "pupilTeacherRatio": 6.5, "numberofAfricanAmericanStudents": 2, "numberofAsianStudents": 5, "numberofHispanicStudents": 7, "numberofIndianStudents": 0, "numberofPacificIslanderStudents": 0, "numberofWhiteStudents": 71, "numberofTwoOrMoreRaceStudents": 0, "numberofUnspecifiedRaceStudents": null}], "isPrivate": true, "privateDays": 205, "privateHours": 7.0, "privateHasLibrary": true, "privateCoed": "Coed", "privateOrientation": "Nonsectarian", "hasBoundary": false}, {"schoolid": "063363005190", "schoolName": "Oakmont High", "phone": "(916) 782-3781", "url": "https://www.schooldigger.com/go/CA/schools/3363005190/school.aspx", "urlCompare": "https://www.schooldigger.com/go/CA/schools/3363005190/search.aspx", "address": {"street": "1710 Cirby Way", "city": "Roseville", "state": "CA", "stateFull": "California", "zip": "95661", "zip4": "5520", "cityURL": "https://www.schooldigger.com/go/CA/city/Roseville/search.aspx", "zipURL": "https://www.schooldigger.com/go/CA/zip/95661/search.aspx", "html": "1710 Cirby Way<br />Roseville, CA 95661-5520"}, "lowGrade": "9", "highGrade": "12", "schoolLevel": "High", "isCharterSchool": "No", "isMagnetSchool": "Yes", "isVirtualSchool": "No", "isTitleISchool": "No", "isTitleISchoolwideSchool": "No", "district": {"districtID": "0633630", "districtName": "Roseville Joint Union High", "url": "https://www.schooldigger.com/go/CA/district/33630/search.aspx", "rankURL": "https://www.schooldigger.com/go/CA/districtrank.aspx?finddistrict=33630"}, "county": {"countyName": "Placer County", "countyURL": "https://www.schooldigger.com/go/CA/county/Placer+County/search.aspx"}, "rankHistory": [{"year": 2019, "rank": 116, "rankOf": 2133, "rankStars": 5, "rankLevel": "High", "rankStatewidePercentage": 94.56, "averageStandardScore": 93.99623}, {"year": 2018, "rank": 247, "rankOf": 2017, "rankStars": 4, "rankLevel": "High", "rankStatewidePercentage": 87.75, "averageStandardScore": 88.24897}], "rankMovement": 131, "schoolYearlyDetails": [{"year": 2020, "numberOfStudents": 2131, "percentFreeDiscLunch": 24.87, "percentofAfricanAmericanStudents": 2.77, "percentofAsianStudents": 19.47, "percentofHispanicStudents": 20.84, "percentofIndianStudents": 0.75, "percentofPacificIslanderStudents": 0.84, "percentofWhiteStudents": 51.06, "percentofTwoOrMoreRaceStudents": 4.27, "percentofUnspecifiedRaceStudents": null, "teachersFulltime": null, "pupilTeacherRatio": null, "numberofAfricanAmericanStudents": 59, "numberofAsianStudents": 415, "numberofHispanicStudents": 444, "numberofIndianStudents": 16, "numberofPacificIslanderStudents": 18, "numberofWhiteStudents": 1088, "numberofTwoOrMoreRaceStudents": 91, "numberofUnspecifiedRaceStudents": null}], "isPrivate": false, "privateDays": null, "privateHours": null, "privateHasLibrary": null, "privateCoed": null, "privateOrientation": null, "hasBoundary": true}, {"schoolid": "061308006167", "schoolName": "Olympus Junior High", "phone": "(916) 782-1667", "url": "https://www.schooldigger.com/go/CA/schools/1308006167/school.aspx", "urlCompare": "https://www.schooldigger.com/go/CA/schools/1308006167/search.aspx", "address": {"street": "2625 La Croix Dr.", "city": "Roseville", "state": "CA", "stateFull": "California", "zip": "95661", "zip4": "3959", "cityURL": "https://www.schooldigger.com/go/CA/city/Roseville/search.aspx", "zipURL": "https://www.schooldigger.com/go/CA/zip/95661/search.aspx", "html": "2625 La Croix Dr.<br />Roseville, CA 95661-3959"}, "lowGrade": "7", "highGrade": "8", "schoolLevel": "Middle", "isCharterSchool": "No", "isMagnetSchool": "No", "isVirtualSchool": "No", "isTitleISchool": "No", "isTitleISchoolwideSchool": "No", "district": {"districtID": "0613080", "districtName": "Eureka Union", "url": "https://www.schooldigger.com/go/CA/district/13080/search.aspx", "rankURL": "https://www.schooldigger.com/go/CA/districtrank.aspx?finddistrict=13080"}, "county": {"countyName": "Placer County", "countyURL": "https://www.schooldigger.com/go/CA/county/Placer+County/search.aspx"}, "rankHistory": [{"year": 2019, "rank": 160, "rankOf": 2715, "rankStars": 5, "rankLevel": "Middle", "rankStatewidePercentage": 94.11, "averageStandardScore": 94.23226}, {"year": 2018, "rank": 145, "rankOf": 2480, "rankStars": 5, "rankLevel": "Middle", "rankStatewidePercentage": 94.15, "averageStandardScore": 94.04527}], "rankMovement": -15, "schoolYearlyDetails": [{"year": 2020, "numberOfStudents": 491, "percentFreeDiscLunch": 16.5, "percentofAfricanAmericanStudents": 2.44, "percentofAsianStudents": 10.59, "percentofHispanicStudents": 15.07, "percentofIndianStudents": 0.41, "percentofPacificIslanderStudents": 0.0, "percentofWhiteStudents": 58.45, "percentofTwoOrMoreRaceStudents": 13.03, "percentofUnspecifiedRaceStudents": null, "teachersFulltime": null, "pupilTeacherRatio": null, "numberofAfricanAmericanStudents": 12, "numberofAsianStudents": 52, "numberofHispanicStudents": 74, "numberofIndianStudents": 2, "numberofPacificIslanderStudents": 0, "numberofWhiteStudents": 287, "numberofTwoOrMoreRaceStudents": 64, "numberofUnspecifiedRaceStudents": null}], "isPrivate": false, "privateDays": null, "privateHours": null, "privateHasLibrary": null, "privateCoed": null, "privateOrientation": null, "hasBoundary": true}, {"schoolid": "063360008761", "schoolName": "Stoneridge Elementary", "phone": "(916) 771-1830", "url": "https://www.schooldigger.com/go/CA/schools/3360008761/school.aspx", "urlCompare": "https://www.schooldigger.com/go/CA/schools/3360008761/search.aspx", "address": {"street": "2501 Alexandra Dr.", "city": "Roseville", "state": "CA", "stateFull": "California", "zip": "95661", "zip4": "4087", "cityURL": "https://www.schooldigger.com/go/CA/city/Roseville/search.aspx", "zipURL": "https://www.schooldigger.com/go/CA/zip/95661/search.aspx", "html": "2501 Alexandra Dr.<br />Roseville, CA 95661-4087"}, "lowGrade": "K", "highGrade": "5", "schoolLevel": "Elementary", "isCharterSchool": "No", "isMagnetSchool": "No", "isVirtualSchool": "No", "isTitleISchool": "No", "isTitleISchoolwideSchool": "No", "district": {"districtID": "0633600", "districtName": "Roseville City Elementary", "url": "https://www.schooldigger.com/go/CA/district/33600/search.aspx", "rankURL": "https://www.schooldigger.com/go/CA/districtrank.aspx?finddistrict=33600"}, "county": {"countyName": "Placer County", "countyURL": "https://www.schooldigger.com/go/CA/county/Placer+County/search.aspx"}, "rankHistory": [{"year": 2019, "rank": 1006, "rankOf": 5789, "rankStars": 4, "rankLevel": "Elementary", "rankStatewidePercentage": 82.62, "averageStandardScore": 83.17097}, {"year": 2018, "rank": 750, "rankOf": 5662, "rankStars": 4, "rankLevel": "Elementary", "rankStatewidePercentage": 86.75, "averageStandardScore": 87.76439}], "rankMovement": -256, "schoolYearlyDetails": [{"year": 2020, "numberOfStudents": 645, "percentFreeDiscLunch": 12.56, "percentofAfricanAmericanStudents": 1.4, "percentofAsianStudents": 18.6, "percentofHispanicStudents": 16.12, "percentofIndianStudents": 0.31, "percentofPacificIslanderStudents": 0.31, "percentofWhiteStudents": 55.35, "percentofTwoOrMoreRaceStudents": 7.91, "percentofUnspecifiedRaceStudents": null, "teachersFulltime": null, "pupilTeacherRatio": null, "numberofAfricanAmericanStudents": 9, "numberofAsianStudents": 120, "numberofHispanicStudents": 104, "numberofIndianStudents": 2, "numberofPacificIslanderStudents": 2, "numberofWhiteStudents": 357, "numberofTwoOrMoreRaceStudents": 51, "numberofUnspecifiedRaceStudents": null}], "isPrivate": false, "privateDays": null, "privateHours": null, "privateHasLibrary": null, "privateCoed": null, "privateOrientation": null, "hasBoundary": true}, {"schoolid": "069999948673", "schoolName": "Sunrise Montessori School Of Roseville, Inc.", "phone": "(916) 722-7772", "url": "https://www.schooldigger.com/go/CA/schools/9999948673/school.aspx", "urlCompare": "https://www.schooldigger.com/go/CA/schools/9999948673/search.aspx", "address": {"street": "8449 Sunrise Blvd", "city": "Roseville", "state": "CA", "stateFull": "California", "zip": "95661", "zip4": "", "cityURL": "https://www.schooldigger.com/go/CA/city/Roseville/search.aspx", "zipURL": "https://www.schooldigger.com/go/CA/zip/95661/search.aspx", "html": "8449 Sunrise Blvd<br />Roseville, CA 95661"}, "lowGrade": "PK", "highGrade": "K", "schoolLevel": "Private", "isCharterSchool": "(n/a)", "isMagnetSchool": "(n/a)", "isVirtualSchool": "(n/a)", "isTitleISchool": "(n/a)", "isTitleISchoolwideSchool": "(n/a)", "county": {"countyName": "Sacramento County", "countyURL": "https://www.schooldigger.com/go/CA/county/Sacramento+County/search.aspx"}, "rankHistory": null, "rankMovement": null, "schoolYearlyDetails": [{"year": 2018, "numberOfStudents": 41, "percentFreeDiscLunch": null, "percentofAfricanAmericanStudents": 0.0, "percentofAsianStudents": 0.0, "percentofHispanicStudents": 0.0, "percentofIndianStudents": 0.0, "percentofPacificIslanderStudents": 0.0, "percentofWhiteStudents": 0.0, "percentofTwoOrMoreRaceStudents": 2.44, "percentofUnspecifiedRaceStudents": null, "teachersFulltime": 4.3, "pupilTeacherRatio": 0.2, "numberofAfricanAmericanStudents": 0, "numberofAsianStudents": 0, "numberofHispanicStudents": 0, "numberofIndianStudents": 0, "numberofPacificIslanderStudents": 0, "numberofWhiteStudents": 0, "numberofTwoOrMoreRaceStudents": 1, "numberofUnspecifiedRaceStudents": null}], "isPrivate": true, "privateDays": 205, "privateHours": 6.0, "privateHasLibrary": true, "privateCoed": "Coed", "privateOrientation": "Nonsectarian", "hasBoundary": false}]}