{"numberOfSchools": 16, "numberOfPages": 2, "schoolList": [{"schoolid": "060681003925", "schoolName": "Blossom Valley Elementary", "phone": "(619) 588-3678", "url": "https://www.schooldigger.com/go/CA/schools/0681003925/school.aspx", "urlCompare": "https://www.schooldigger.com/go/CA/schools/0681003925/search.aspx", "address": {"street": "9863 Oakmont Terr.", "city": "El Cajon", "state": "CA", "stateFull": "California", "zip": "92021", "zip4": "2300", "cityURL": "https://www.schooldigger.com/go/CA/city/El+Cajon/search.aspx", "zipURL": "https://www.schooldigger.com/go/CA/zip/92021/search.aspx", "html": "9863 Oakmont Terr.<br />El Cajon, CA 92021-2300"}, "lowGrade": "K", "highGrade": "5", "schoolLevel": "Elementary", "isCharterSchool": "No", "isMagnetSchool": "No", "isVirtualSchool": "No", "isTitleISchool": "No", "isTitleISchoolwideSchool": "No", "district": {"districtID": "0606810", "districtName": "Cajon Valley Union", "url": "https://www.schooldigger.com/go/CA/district/06810/search.aspx", "rankURL": "https://www.schooldigger.com/go/CA/districtrank.aspx?finddistrict=06810"}, "county": {"countyName": "San Diego County", "countyURL": "https://www.schooldigger.com/go/CA/county/San+Diego+County/search.aspx"}, "rankHistory": [{"year": 2019, "rank": 1033, "rankOf": 5789, "rankStars": 4, "rankLevel": "Elementary", "rankStatewidePercentage": 82.16, "averageStandardScore": 82.65938}, {"year": 2018, "rank": 1030, "rankOf": 5662, "rankStars": 4, "rankLevel": "Elementary", "rankStatewidePercentage": 81.81, "averageStandardScore": 82.02456}], "rankMovement": -3, "schoolYearlyDetails": [{"year": 2020, "numberOfStudents": 561, "percentFreeDiscLunch": 30.84, "percentofAfricanAmericanStudents": 1.25, "percentofAsianStudents": 2.5, "percentofHispanicStudents": 25.67, "percentofIndianStudents": 0.0, "percentofPacificIslanderStudents": 0.71, "percentofWhiteStudents": 66.13, "percentofTwoOrMoreRaceStudents": 3.74, "percentofUnspecifiedRaceStudents": null, "teachersFulltime": null, "pupilTeacherRatio": null, "numberofAfricanAmericanStudents": 7, "numberofAsianStudents": 14, "numberofHispanicStudents": 144, "numberofIndianStudents": 0, "numberofPacificIslanderStudents": 4, "numberofWhiteStudents": 371, "numberofTwoOrMoreRaceStudents": 21, "numberofUnspecifiedRaceStudents": null}], "isPrivate": false, "privateDays": null, "privateHours": null, "privateHasLibrary": null, "privateCoed": null, "privateOrientation": null, "hasBoundary": true}, {"schoolid": "060681000606", "schoolName": "Bostonia Language Academy", "phone": "(619) 588-3121", "url": "https://www.schooldigger.com/go/CA/schools/0681000606/school.aspx", "urlCompare": "https://www.schooldigger.com/go/CA/schools/0681000606/search.aspx", "address": {"street": "1390 E. BRd.way", "city": "El Cajon", "state": "CA", "stateFull": "California", "zip": "92021", "zip4": "5812", "cityURL": "https://www.schooldigger.com/go/CA/city/El+Cajon/search.aspx", "zipURL": "https://www.schooldigger.com/go/CA/zip/92021/search.aspx", "html": "1390 E. BRd.way<br />El Cajon, CA 92021-5812"}, "lowGrade": "K", "highGrade": "5", "schoolLevel": "Elementary", "isCharterSchool": "No", "isMagnetSchool": "No", "isVirtualSchool": "No", "isTitleISchool": "Yes", "isTitleISchoolwideSchool": "No", "district": {"districtID": "0606810", "districtName": "Cajon Valley Union", "url": "https://www.schooldigger.com/go/CA/district/06810/search.aspx", "rankURL": "https://www.schooldigger.com/go/CA/districtrank.aspx?finddistrict=06810"}, "county": {"countyName": "San Diego County", "countyURL": "https://www.schooldigger.com/go/CA/county/San+Diego+County/search.aspx"}, "rankHistory": [{"year": 2019, "rank": 2144, "rankOf": 5789, "rankStars": 3, "rankLevel": "Elementary", "rankStatewidePercentage": 62.96, "averageStandardScore": 58.61906}, {"year": 2018, "rank": 1673, "rankOf": 5662, "rankStars": 4, "rankLevel": "Elementary", "rankStatewidePercentage": 70.45, "averageStandardScore": 68.08737}], "rankMovement": -471, "schoolYearlyDetails": [{"year": 2020, "numberOfStudents": 639, "percentFreeDiscLunch": 70.11, "percentofAfricanAmericanStudents": 4.85, "percentofAsianStudents": 0.47, "percentofHispanicStudents": 76.53, "percentofIndianStudents": 0.31, "percentofPacificIslanderStudents": 0.0, "percentofWhiteStudents": 10.8, "percentofTwoOrMoreRaceStudents": 7.04, "percentofUnspecifiedRaceStudents": null, "teachersFulltime": null, "pupilTeacherRatio": null, "numberofAfricanAmericanStudents": 31, "numberofAsianStudents": 3, "numberofHispanicStudents": 489, "numberofIndianStudents": 2, "numberofPacificIslanderStudents": 0, "numberofWhiteStudents": 69, "numberofTwoOrMoreRaceStudents": 45, "numberofUnspecifiedRaceStudents": null}], "isPrivate": false, "privateDays": null, "privateHours": null, "privateHasLibrary": null, "privateCoed": null, "privateOrientation": null, "hasBoundary": true}, {"schoolid": "060681008590", "schoolName": "Cajon Valley Home", "phone": "(619) 588-3128", "url": "https://www.schooldigger.com/go/CA/schools/0681008590/school.aspx", "urlCompare": "https://www.schooldigger.com/go/CA/schools/0681008590/search.aspx", "address": {"street": "1384 BRd.way", "city": "El Cajon", "state": "CA", "stateFull": "California", "zip": "92021", "zip4": "5812", "cityURL": "https://www.schooldigger.com/go/CA/city/El+Cajon/search.aspx", "zipURL": "https://www.schooldigger.com/go/CA/zip/92021/search.aspx", "html": "1384 BRd.way<br />El Cajon, CA 92021-5812"}, "lowGrade": "K", "highGrade": "8", "schoolLevel": "Elementary", "isCharterSchool": "No", "isMagnetSchool": "No", "isVirtualSchool": "No", "isTitleISchool": "No", "isTitleISchoolwideSchool": "No", "district": {"districtID": "0606810", "districtName": "Cajon Valley Union", "url": "https://www.schooldigger.com/go/CA/district/06810/search.aspx", "rankURL": "https://www.schooldigger.com/go/CA/districtrank.aspx?finddistrict=06810"}, "county": {"countyName": "San Diego County", "countyURL": "https://www.schooldigger.com/go/CA/county/San+Diego+County/search.aspx"}, "rankHistory": null, "rankMovement": null, "schoolYearlyDetails": [{"year": 2020, "numberOfStudents": 40, "percentFreeDiscLunch": 67.5, "percentofAfricanAmericanStudents": 5.0, "percentofAsianStudents": 5.0, "percentofHispanicStudents": 42.5, "percentofIndianStudents": 0.0, "percentofPacificIslanderStudents": 0.0, "percentofWhiteStudents": 35.0, "percentofTwoOrMoreRaceStudents": 12.5, "percentofUnspecifiedRaceStudents": null, "teachersFulltime": null, "pupilTeacherRatio": null, "numberofAfricanAmericanStudents": 2, "numberofAsianStudents": 2, "numberofHispanicStudents": 17, "numberofIndianStudents": 0, "numberofPacificIslanderStudents": 0, "numberofWhiteStudents": 14, "numberofTwoOrMoreRaceStudents": 5, "numberofUnspecifiedRaceStudents": null}], "isPrivate": false, "privateDays": null, "privateHours": null, "privateHasLibrary": null, "privateCoed": null, "privateOrientation": null, "hasBoundary": false}, {"schoolid": "060681000609", "schoolName": "Crest Elementary", "phone": "(619) 558-3128", "url": "https://www.schooldigger.com/go/CA/schools/0681000609/school.aspx", "urlCompare": "https://www.schooldigger.com/go/CA/schools/0681000609/search.aspx", "address": {"street": "2000 Suncrest Blvd.", "city": "El Cajon", "state": "CA", "stateFull": "California", "zip": "92021", "zip4": "4249", "cityURL": "https://www.schooldigger.com/go/CA/city/El+Cajon/search.aspx", "zipURL": "https://www.schooldigger.com/go/CA/zip/92021/search.aspx", "html": "2000 Suncrest Blvd.<br />El Cajon, CA 92021-4249"}, "lowGrade": "K", "highGrade": "5", "schoolLevel": "Elementary", "isCharterSchool": "No", "isMagnetSchool": "No", "isVirtualSchool": "No", "isTitleISchool": "No", "isTitleISchoolwideSchool": "No", "district": {"districtID": "0606810", "districtName": "Cajon Valley Union", "url": "https://www.schooldigger.com/go/CA/district/06810/search.aspx", "rankURL": "https://www.schooldigger.com/go/CA/districtrank.aspx?finddistrict=06810"}, "county": {"countyName": "San Diego County", "countyURL": "https://www.schooldigger.com/go/CA/county/San+Diego+County/search.aspx"}, "rankHistory": [{"year": 2019, "rank": 2437, "rankOf": 5789, "rankStars": 3, "rankLevel": "Elementary", "rankStatewidePercentage": 57.9, "averageStandardScore": 52.76798}, {"year": 2018, "rank": 2856, "rankOf": 5662, "rankStars": 2, "rankLevel": "Elementary", "rankStatewidePercentage": 49.56, "averageStandardScore": 44.50686}], "rankMovement": 419, "schoolYearlyDetails": [{"year": 2020, "numberOfStudents": 105, "percentFreeDiscLunch": 36.19, "percentofAfricanAmericanStudents": 3.81, "percentofAsianStudents": 0.95, "percentofHispanicStudents": 25.71, "percentofIndianStudents": 0.95, "percentofPacificIslanderStudents": 0.0, "percentofWhiteStudents": 50.48, "percentofTwoOrMoreRaceStudents": 18.1, "percentofUnspecifiedRaceStudents": null, "teachersFulltime": null, "pupilTeacherRatio": null, "numberofAfricanAmericanStudents": 4, "numberofAsianStudents": 1, "numberofHispanicStudents": 27, "numberofIndianStudents": 1, "numberofPacificIslanderStudents": 0, "numberofWhiteStudents": 53, "numberofTwoOrMoreRaceStudents": 19, "numberofUnspecifiedRaceStudents": null}], "isPrivate": false, "privateDays": null, "privateHours": null, "privateHasLibrary": null, "privateCoed": null, "privateOrientation": null, "hasBoundary": true}, {"schoolid": "060238614301", "schoolName": "Diego Valley East Public Charter", "phone": "(619) 870-0608", "url": "https://www.schooldigger.com/go/CA/schools/0238614301/school.aspx", "urlCompare": "https://www.schooldigger.com/go/CA/schools/0238614301/search.aspx", "address": {"street": "511 N. Second St.", "city": "El Cajon", "state": "CA", "stateFull": "California", "zip": "92021", "zip4": "6449", "cityURL": "https://www.schooldigger.com/go/CA/city/El+Cajon/search.aspx", "zipURL": "https://www.schooldigger.com/go/CA/zip/92021/search.aspx", "html": "511 N. Second St.<br />El Cajon, CA 92021-6449"}, "lowGrade": "K", "highGrade": "12", "schoolLevel": "Other", "isCharterSchool": "Yes", "isMagnetSchool": "No", "isVirtualSchool": "No", "isTitleISchool": "(n/a)", "isTitleISchoolwideSchool": "(n/a)", "district": {"districtID": "0602386", "districtName": "Diego Valley East Public Charter District", "url": "https://www.schooldigger.com/go/CA/district/02386/search.aspx", "rankURL": "https://www.schooldigger.com/go/CA/districtrank.aspx?finddistrict=02386"}, "county": {"countyName": "San Diego County", "countyURL": "https://www.schooldigger.com/go/CA/county/San+Diego+County/search.aspx"}, "rankHistory": null, "rankMovement": null, "schoolYearlyDetails": [{"year": 2020, "numberOfStudents": 347, "percentFreeDiscLunch": 81.56, "percentofAfricanAmericanStudents": 5.48, "percentofAsianStudents": 1.44, "percentofHispanicStudents": 40.35, "percentofIndianStudents": 2.31, "percentofPacificIslanderStudents": 0.58, "percentofWhiteStudents": 44.38, "percentofTwoOrMoreRaceStudents": 5.48, "percentofUnspecifiedRaceStudents": null, "teachersFulltime": null, "pupilTeacherRatio": null, "numberofAfricanAmericanStudents": 19, "numberofAsianStudents": 5, "numberofHispanicStudents": 140, "numberofIndianStudents": 8, "numberofPacificIslanderStudents": 2, "numberofWhiteStudents": 154, "numberofTwoOrMoreRaceStudents": 19, "numberofUnspecifiedRaceStudents": null}], "isPrivate": false, "privateDays": null, "privateHours": null, "privateHasLibrary": null, "privateCoed": null, "privateOrientation": null, "hasBoundary": false}, {"schoolid": "061623002018", "schoolName": "El Cajon Valley High", "phone": "(619) 579-5855", "url": "https://www.schooldigger.com/go/CA/schools/1623002018/school.aspx", "urlCompare": "https://www.schooldigger.com/go/CA/schools/1623002018/search.aspx", "address": {"street": "1035 E. Madison Ave.", "city": "El Cajon", "state": "CA", "stateFull": "California", "zip": "92021", "zip4": "6226", "cityURL": "https://www.schooldigger.com/go/CA/city/El+Cajon/search.aspx", "zipURL": "https://www.schooldigger.com/go/CA/zip/92021/search.aspx", "html": "1035 E. Madison Ave.<br />El Cajon, CA 92021-6226"}, "lowGrade": "9", "highGrade": "12", "schoolLevel": "High", "isCharterSchool": "No", "isMagnetSchool": "No", "isVirtualSchool": "No", "isTitleISchool": "Yes", "isTitleISchoolwideSchool": "No", "district": {"districtID": "0616230", "districtName": "Grossmont Union High", "url": "https://www.schooldigger.com/go/CA/district/16230/search.aspx", "rankURL": "https://www.schooldigger.com/go/CA/districtrank.aspx?finddistrict=16230"}, "county": {"countyName": "San Diego County", "countyURL": "https://www.schooldigger.com/go/CA/county/San+Diego+County/search.aspx"}, "rankHistory": [{"year": 2019, "rank": 1576, "rankOf": 2133, "rankStars": 1, "rankLevel": "High", "rankStatewidePercentage": 26.11, "averageStandardScore": 21.7371}, {"year": 2018, "rank": 1207, "rankOf": 2017, "rankStars": 2, "rankLevel": "High", "rankStatewidePercentage": 40.16, "averageStandardScore": 40.36537}], "rankMovement": -369, "schoolYearlyDetails": [{"year": 2020, "numberOfStudents": 1557, "percentFreeDiscLunch": 90.04, "percentofAfricanAmericanStudents": 9.51, "percentofAsianStudents": 3.53, "percentofHispanicStudents": 43.74, "percentofIndianStudents": 0.32, "percentofPacificIslanderStudents": 0.51, "percentofWhiteStudents": 40.53, "percentofTwoOrMoreRaceStudents": 1.86, "percentofUnspecifiedRaceStudents": null, "teachersFulltime": null, "pupilTeacherRatio": null, "numberofAfricanAmericanStudents": 148, "numberofAsianStudents": 55, "numberofHispanicStudents": 681, "numberofIndianStudents": 5, "numberofPacificIslanderStudents": 8, "numberofWhiteStudents": 631, "numberofTwoOrMoreRaceStudents": 29, "numberofUnspecifiedRaceStudents": null}], "isPrivate": false, "privateDays": null, "privateHours": null, "privateHasLibrary": null, "privateCoed": null, "privateOrientation": null, "hasBoundary": true}, {"schoolid": "060681000615", "schoolName": "Greenfield Middle", "phone": "(619) 588-3103", "url": "https://www.schooldigger.com/go/CA/schools/0681000615/school.aspx", "urlCompare": "https://www.schooldigger.com/go/CA/schools/0681000615/search.aspx", "address": {"street": "1495 Greenfield Dr.", "city": "El Cajon", "state": "CA", "stateFull": "California", "zip": "92021", "zip4": "3414", "cityURL": "https://www.schooldigger.com/go/CA/city/El+Cajon/search.aspx", "zipURL": "https://www.schooldigger.com/go/CA/zip/92021/search.aspx", "html": "1495 Greenfield Dr.<br />El Cajon, CA 92021-3414"}, "lowGrade": "6", "highGrade": "8", "schoolLevel": "Middle", "isCharterSchool": "No", "isMagnetSchool": "No", "isVirtualSchool": "No", "isTitleISchool": "Yes", "isTitleISchoolwideSchool": "No", "district": {"districtID": "0606810", "districtName": "Cajon Valley Union", "url": "https://www.schooldigger.com/go/CA/district/06810/search.aspx", "rankURL": "https://www.schooldigger.com/go/CA/districtrank.aspx?finddistrict=06810"}, "county": {"countyName": "San Diego County", "countyURL": "https://www.schooldigger.com/go/CA/county/San+Diego+County/search.aspx"}, "rankHistory": [{"year": 2019, "rank": 2257, "rankOf": 2715, "rankStars": 1, "rankLevel": "Middle", "rankStatewidePercentage": 16.87, "averageStandardScore": 18.37225}, {"year": 2018, "rank": 2041, "rankOf": 2480, "rankStars": 1, "rankLevel": "Middle", "rankStatewidePercentage": 17.7, "averageStandardScore": 19.17066}], "rankMovement": -216, "schoolYearlyDetails": [{"year": 2020, "numberOfStudents": 800, "percentFreeDiscLunch": 84.5, "percentofAfricanAmericanStudents": 8.0, "percentofAsianStudents": 2.62, "percentofHispanicStudents": 55.0, "percentofIndianStudents": 0.38, "percentofPacificIslanderStudents": 0.5, "percentofWhiteStudents": 27.75, "percentofTwoOrMoreRaceStudents": 5.75, "percentofUnspecifiedRaceStudents": null, "teachersFulltime": null, "pupilTeacherRatio": null, "numberofAfricanAmericanStudents": 64, "numberofAsianStudents": 21, "numberofHispanicStudents": 440, "numberofIndianStudents": 3, "numberofPacificIslanderStudents": 4, "numberofWhiteStudents": 222, "numberofTwoOrMoreRaceStudents": 46, "numberofUnspecifiedRaceStudents": null}], "isPrivate": false, "privateDays": null, "privateHours": null, "privateHasLibrary": null, "privateCoed": null, "privateOrientation": null, "hasBoundary": true}, {"schoolid": "060249514409", "schoolName": "Kidinnu Academy", "phone": "(619) 938-4864", "url": "https://www.schooldigger.com/go/CA/schools/0249514409/school.aspx", "urlCompare": "https://www.schooldigger.com/go/CA/schools/0249514409/search.aspx", "address": {"street": "1025 N. Second St.", "city": "El Cajon", "state": "CA", "stateFull": "California", "zip": "92021", "zip4": "5844", "cityURL": "https://www.schooldigger.com/go/CA/city/El+Cajon/search.aspx", "zipURL": "https://www.schooldigger.com/go/CA/zip/92021/search.aspx", "html": "1025 N. Second St.<br />El Cajon, CA 92021-5844"}, "lowGrade": "K", "highGrade": "5", "schoolLevel": "Elementary", "isCharterSchool": "Yes", "isMagnetSchool": "No", "isVirtualSchool": "No", "isTitleISchool": "Yes", "isTitleISchoolwideSchool": "No", "district": {"districtID": "0602495", "districtName": "Kidinnu Academy District", "url": "https://www.schooldigger.com/go/CA/district/02495/search.aspx", "rankURL": "https://www.schooldigger.com/go/CA/districtrank.aspx?finddistrict=02495"}, "county": {"countyName": "San Diego County", "countyURL": "https://www.schooldigger.com/go/CA/county/San+Diego+County/search.aspx"}, "rankHistory": null, "rankMovement": null, "schoolYearlyDetails": [{"year": 2020, "numberOfStudents": 115, "percentFreeDiscLunch": 91.3, "percentofAfricanAmericanStudents": 0.0, "percentofAsianStudents": 0.0, "percentofHispanicStudents": 1.74, "percentofIndianStudents": 0.0, "percentofPacificIslanderStudents": 0.0, "percentofWhiteStudents": 98.26, "percentofTwoOrMoreRaceStudents": 0.0, "percentofUnspecifiedRaceStudents": null, "teachersFulltime": null, "pupilTeacherRatio": null, "numberofAfricanAmericanStudents": 0, "numberofAsianStudents": 0, "numberofHispanicStudents": 2, "numberofIndianStudents": 0, "numberofPacificIslanderStudents": 0, "numberofWhiteStudents": 113, "numberofTwoOrMoreRaceStudents": 0, "numberofUnspecifiedRaceStudents": null}], "isPrivate": false, "privateDays": null, "privateHours": null, "privateHasLibrary": null, "privateCoed": null, "privateOrientation": null, "hasBoundary": false}, {"schoolid": "060681011751", "schoolName": "Los Coches Creek Middle", "phone": "(619) 441-5741", "url": "https://www.schooldigger.com/go/CA/schools/0681011751/school.aspx", "urlCompare": "https://www.schooldigger.com/go/CA/schools/0681011751/search.aspx", "address": {"street": "9669 Dunbar Ln.", "city": "El Cajon", "state": "CA", "stateFull": "California", "zip": "92021", "zip4": "2619", "cityURL": "https://www.schooldigger.com/go/CA/city/El+Cajon/search.aspx", "zipURL": "https://www.schooldigger.com/go/CA/zip/92021/search.aspx", "html": "9669 Dunbar Ln.<br />El Cajon, CA 92021-2619"}, "lowGrade": "6", "highGrade": "8", "schoolLevel": "Middle", "isCharterSchool": "No", "isMagnetSchool": "No", "isVirtualSchool": "No", "isTitleISchool": "No", "isTitleISchoolwideSchool": "No", "district": {"districtID": "0606810", "districtName": "Cajon Valley Union", "url": "https://www.schooldigger.com/go/CA/district/06810/search.aspx", "rankURL": "https://www.schooldigger.com/go/CA/districtrank.aspx?finddistrict=06810"}, "county": {"countyName": "San Diego County", "countyURL": "https://www.schooldigger.com/go/CA/county/San+Diego+County/search.aspx"}, "rankHistory": [{"year": 2019, "rank": 817, "rankOf": 2715, "rankStars": 3, "rankLevel": "Middle", "rankStatewidePercentage": 69.91, "averageStandardScore": 63.89499}, {"year": 2018, "rank": 736, "rankOf": 2480, "rankStars": 4, "rankLevel": "Middle", "rankStatewidePercentage": 70.32, "averageStandardScore": 65.47884}], "rankMovement": -81, "schoolYearlyDetails": [{"year": 2020, "numberOfStudents": 842, "percentFreeDiscLunch": 37.65, "percentofAfricanAmericanStudents": 2.02, "percentofAsianStudents": 1.19, "percentofHispanicStudents": 29.57, "percentofIndianStudents": 0.83, "percentofPacificIslanderStudents": 0.83, "percentofWhiteStudents": 59.74, "percentofTwoOrMoreRaceStudents": 5.82, "percentofUnspecifiedRaceStudents": null, "teachersFulltime": null, "pupilTeacherRatio": null, "numberofAfricanAmericanStudents": 17, "numberofAsianStudents": 10, "numberofHispanicStudents": 249, "numberofIndianStudents": 7, "numberofPacificIslanderStudents": 7, "numberofWhiteStudents": 503, "numberofTwoOrMoreRaceStudents": 49, "numberofUnspecifiedRaceStudents": null}], "isPrivate": false, "privateDays": null, "privateHours": null, "privateHasLibrary": null, "privateCoed": null, "privateOrientation": null, "hasBoundary": true}, {"schoolid": "060681000620", "schoolName": "Magnolia Elementary", "phone": "(619) 588-3080", "url": "https://www.schooldigger.com/go/CA/schools/0681000620/school.aspx", "urlCompare": "https://www.schooldigger.com/go/CA/schools/0681000620/search.aspx", "address": {"street": "650 Greenfield Dr.", "city": "El Cajon", "state": "CA", "stateFull": "California", "zip": "92021", "zip4": "2957", "cityURL": "https://www.schooldigger.com/go/CA/city/El+Cajon/search.aspx", "zipURL": "https://www.schooldigger.com/go/CA/zip/92021/search.aspx", "html": "650 Greenfield Dr.<br />El Cajon, CA 92021-2957"}, "lowGrade": "K", "highGrade": "5", "schoolLevel": "Elementary", "isCharterSchool": "No", "isMagnetSchool": "No", "isVirtualSchool": "No", "isTitleISchool": "Yes", "isTitleISchoolwideSchool": "No", "district": {"districtID": "0606810", "districtName": "Cajon Valley Union", "url": "https://www.schooldigger.com/go/CA/district/06810/search.aspx", "rankURL": "https://www.schooldigger.com/go/CA/districtrank.aspx?finddistrict=06810"}, "county": {"countyName": "San Diego County", "countyURL": "https://www.schooldigger.com/go/CA/county/San+Diego+County/search.aspx"}, "rankHistory": [{"year": 2019, "rank": 5517, "rankOf": 5789, "rankStars": 0, "rankLevel": "Elementary", "rankStatewidePercentage": 4.7, "averageStandardScore": 10.8588}, {"year": 2018, "rank": 5352, "rankOf": 5662, "rankStars": 0, "rankLevel": "Elementary", "rankStatewidePercentage": 5.48, "averageStandardScore": 11.48225}], "rankMovement": -165, "schoolYearlyDetails": [{"year": 2020, "numberOfStudents": 561, "percentFreeDiscLunch": 86.27, "percentofAfricanAmericanStudents": 11.23, "percentofAsianStudents": 5.7, "percentofHispanicStudents": 49.55, "percentofIndianStudents": 0.18, "percentofPacificIslanderStudents": 1.25, "percentofWhiteStudents": 27.09, "percentofTwoOrMoreRaceStudents": 4.99, "percentofUnspecifiedRaceStudents": null, "teachersFulltime": null, "pupilTeacherRatio": null, "numberofAfricanAmericanStudents": 63, "numberofAsianStudents": 32, "numberofHispanicStudents": 278, "numberofIndianStudents": 1, "numberofPacificIslanderStudents": 7, "numberofWhiteStudents": 152, "numberofTwoOrMoreRaceStudents": 28, "numberofUnspecifiedRaceStudents": null}], "isPrivate": false, "privateDays": null, "privateHours": null, "privateHasLibrary": null, "privateCoed": null, "privateOrientation": null, "hasBoundary": true}]}